{
  "success": true,
  "estadisticas_globales": {
    "inicio": "2025-10-09 21:19:31.497118",
    "fin": "2025-10-09 21:42:17.013470",
    "tiendas_procesadas": 1,
    "meses_procesados": 2,
    "registros_totales": 769369,
    "errores_totales": 0,
    "tiempo_total": 1365.516352
  },
  "resumen": {
    "total_tareas": 2,
    "exitosas": 2,
    "fallidas": 0,
    "tasa_exito": 100.0,
    "registros_totales": 769369,
    "tiempo_promedio_tarea": 998.4344923496246,
    "registros_por_segundo": 563.4271598968006
  },
  "estadisticas_tiendas": {
    "tienda_10": {
      "periodos_exitosos": 2,
      "registros_total": 769369,
      "tiempo_total": 1996.8689846992493
    }
  },
  "errores": []
}